<?xml version="1.0"?>
<MixxxMIDIPreset mixxxVersion="1.11.0+" schemaVersion="1">
  <!-- created Tue Jun 18 2013 22:33:42 GMT+0200 (CEST) -->
  <!-- script version 2.2 -->
  <info>
    <name>Reloop RMP-3</name>
    <author>Thomas Brand</author>
    <description>Custom Bindings for Reloop RMP-3 Cross Media Player</description>
  </info>
  <controller id="RMP-3">
    <scriptfiles>
      <file functionprefix="c" filename="Reloop-RMP-3-scripts.js"/>
    </scriptfiles>
    <controls>
      <!--_0x01_0-->
      <control>
        <midino>0x01</midino>
        <status>0x90</status>
        <description/>
        <group>[Channel1]</group>
        <key>c.playTrack</key>
        <options>
          <script-binding/>
        </options>
      </control>
      <!--_0x01_1-->
      <control>
        <midino>0x01</midino>
        <status>0x91</status>
        <description/>
        <group>[Channel2]</group>
        <key>c.playTrack</key>
        <options>
          <script-binding/>
        </options>
      </control>
      <!--_0x07_0-->
      <control>
        <midino>0x07</midino>
        <status>0x90</status>
        <description/>
        <group>[Channel1]</group>
        <key>c.Cue</key>
        <options>
          <script-binding/>
        </options>
      </control>
      <!--_0x07_1-->
      <control>
        <midino>0x07</midino>
        <status>0x91</status>
        <description/>
        <group>[Channel2]</group>
        <key>c.Cue</key>
        <options>
          <script-binding/>
        </options>
      </control>
      <!--_0x1e_0-->
      <control>
        <midino>0x1e</midino>
        <status>0x90</status>
        <description/>
        <group>[Channel1]</group>
        <key>filterHighKill</key>
        <options>
          <normal/>
        </options>
      </control>
      <!--_0x1e_1-->
      <control>
        <midino>0x1e</midino>
        <status>0x91</status>
        <description/>
        <group>[Channel2]</group>
        <key>filterHighKill</key>
        <options>
          <normal/>
        </options>
      </control>
      <!--_0x0c_0-->
      <control>
        <midino>0x0c</midino>
        <status>0x90</status>
        <description/>
        <group>[Channel1]</group>
        <key>filterMidKill</key>
        <options>
          <normal/>
        </options>
      </control>
      <!--_0x0c_1-->
      <control>
        <midino>0x0c</midino>
        <status>0x91</status>
        <description/>
        <group>[Channel2]</group>
        <key>filterMidKill</key>
        <options>
          <normal/>
        </options>
      </control>
      <!--_0x12_0-->
      <control>
        <midino>0x12</midino>
        <status>0x90</status>
        <description/>
        <group>[Channel1]</group>
        <key>filterLowKill</key>
        <options>
          <normal/>
        </options>
      </control>
      <!--_0x12_1-->
      <control>
        <midino>0x12</midino>
        <status>0x91</status>
        <description/>
        <group>[Channel2]</group>
        <key>filterLowKill</key>
        <options>
          <normal/>
        </options>
      </control>
      <!--_0x29_0-->
      <control>
        <midino>0x29</midino>
        <status>0x90</status>
        <description/>
        <group>[Channel1]</group>
        <key>repeat</key>
        <options>
          <normal/>
        </options>
      </control>
      <!--_0x29_1-->
      <control>
        <midino>0x29</midino>
        <status>0x91</status>
        <description/>
        <group>[Channel2]</group>
        <key>repeat</key>
        <options>
          <normal/>
        </options>
      </control>
      <!--_0x11_0-->
      <control>
        <midino>0x11</midino>
        <status>0x90</status>
        <description/>
        <group>[Channel1]</group>
        <key>beats_translate_curpos</key>
        <options>
          <normal/>
        </options>
      </control>
      <!--_0x11_1-->
      <control>
        <midino>0x11</midino>
        <status>0x91</status>
        <description/>
        <group>[Channel2]</group>
        <key>beats_translate_curpos</key>
        <options>
          <normal/>
        </options>
      </control>
      <!--_0x0b_0-->
      <control>
        <midino>0x0b</midino>
        <status>0x90</status>
        <description/>
        <group>[Channel1]</group>
        <key>quantize</key>
        <options>
          <normal/>
        </options>
      </control>
      <!--_0x0b_1-->
      <control>
        <midino>0x0b</midino>
        <status>0x91</status>
        <description/>
        <group>[Channel2]</group>
        <key>quantize</key>
        <options>
          <normal/>
        </options>
      </control>
      <!--_0x14_0-->
      <control>
        <midino>0x14</midino>
        <status>0x90</status>
        <description/>
        <group>[Channel1]</group>
        <key>keylock</key>
        <options>
          <normal/>
        </options>
      </control>
      <!--_0x14_1-->
      <control>
        <midino>0x14</midino>
        <status>0x91</status>
        <description/>
        <group>[Channel2]</group>
        <key>keylock</key>
        <options>
          <normal/>
        </options>
      </control>
      <!--_0x19_0-->
      <control>
        <midino>0x19</midino>
        <status>0x90</status>
        <description/>
        <group>[Channel1]</group>
        <key>start</key>
        <options>
          <normal/>
        </options>
      </control>
      <!--_0x19_1-->
      <control>
        <midino>0x19</midino>
        <status>0x91</status>
        <description/>
        <group>[Channel2]</group>
        <key>start</key>
        <options>
          <normal/>
        </options>
      </control>
      <!--_0x25_0-->
      <control>
        <midino>0x25</midino>
        <status>0x90</status>
        <description/>
        <group>[Playlist]</group>
        <key>SelectPrevPlaylist</key>
        <options>
          <normal/>
        </options>
      </control>
      <!--_0x25_1-->
      <control>
        <midino>0x25</midino>
        <status>0x91</status>
        <description/>
        <group>[Playlist]</group>
        <key>SelectPrevPlaylist</key>
        <options>
          <normal/>
        </options>
      </control>
      <!--_0x1f_0-->
      <control>
        <midino>0x1f</midino>
        <status>0x90</status>
        <description/>
        <group>[Playlist]</group>
        <key>SelectNextPlaylist</key>
        <options>
          <normal/>
        </options>
      </control>
      <!--_0x1f_1-->
      <control>
        <midino>0x1f</midino>
        <status>0x91</status>
        <description/>
        <group>[Playlist]</group>
        <key>SelectNextPlaylist</key>
        <options>
          <normal/>
        </options>
      </control>
      <!--_0x1c_0-->
      <control>
        <midino>0x1c</midino>
        <status>0x90</status>
        <description/>
        <group>[Channel1]</group>
        <key>hotcue_1_activate</key>
        <options>
          <normal/>
        </options>
      </control>
      <!--_0x1c_1-->
      <control>
        <midino>0x1c</midino>
        <status>0x91</status>
        <description/>
        <group>[Channel2]</group>
        <key>hotcue_1_activate</key>
        <options>
          <normal/>
        </options>
      </control>
      <!--_0x0a_0-->
      <control>
        <midino>0x0a</midino>
        <status>0x90</status>
        <description/>
        <group>[Channel1]</group>
        <key>hotcue_2_activate</key>
        <options>
          <normal/>
        </options>
      </control>
      <!--_0x0a_1-->
      <control>
        <midino>0x0a</midino>
        <status>0x91</status>
        <description/>
        <group>[Channel2]</group>
        <key>hotcue_2_activate</key>
        <options>
          <normal/>
        </options>
      </control>
      <!--_0x10_0-->
      <control>
        <midino>0x10</midino>
        <status>0x90</status>
        <description/>
        <group>[Channel1]</group>
        <key>hotcue_3_activate</key>
        <options>
          <normal/>
        </options>
      </control>
      <!--_0x10_1-->
      <control>
        <midino>0x10</midino>
        <status>0x91</status>
        <description/>
        <group>[Channel2]</group>
        <key>hotcue_3_activate</key>
        <options>
          <normal/>
        </options>
      </control>
      <!--_0x0f_0-->
      <control>
        <midino>0x0f</midino>
        <status>0x90</status>
        <description/>
        <group>[Channel1]</group>
        <key>hotcue_4_activate</key>
        <options>
          <normal/>
        </options>
      </control>
      <!--_0x0f_1-->
      <control>
        <midino>0x0f</midino>
        <status>0x91</status>
        <description/>
        <group>[Channel2]</group>
        <key>hotcue_4_activate</key>
        <options>
          <normal/>
        </options>
      </control>
      <!--_0x5b_0-->
      <control>
        <midino>0x5b</midino>
        <status>0x90</status>
        <description/>
        <group>[Channel1]</group>
        <key>hotcue_1_clear</key>
        <options>
          <normal/>
        </options>
      </control>
      <!--_0x5b_1-->
      <control>
        <midino>0x5b</midino>
        <status>0x91</status>
        <description/>
        <group>[Channel2]</group>
        <key>hotcue_1_clear</key>
        <options>
          <normal/>
        </options>
      </control>
      <!--_0x49_0-->
      <control>
        <midino>0x49</midino>
        <status>0x90</status>
        <description/>
        <group>[Channel1]</group>
        <key>hotcue_2_clear</key>
        <options>
          <normal/>
        </options>
      </control>
      <!--_0x49_1-->
      <control>
        <midino>0x49</midino>
        <status>0x91</status>
        <description/>
        <group>[Channel2]</group>
        <key>hotcue_2_clear</key>
        <options>
          <normal/>
        </options>
      </control>
      <!--_0x4f_0-->
      <control>
        <midino>0x4f</midino>
        <status>0x90</status>
        <description/>
        <group>[Channel1]</group>
        <key>hotcue_3_clear</key>
        <options>
          <normal/>
        </options>
      </control>
      <!--_0x4f_1-->
      <control>
        <midino>0x4f</midino>
        <status>0x91</status>
        <description/>
        <group>[Channel2]</group>
        <key>hotcue_3_clear</key>
        <options>
          <normal/>
        </options>
      </control>
      <!--_0x4e_0-->
      <control>
        <midino>0x4e</midino>
        <status>0x90</status>
        <description/>
        <group>[Channel1]</group>
        <key>hotcue_4_clear</key>
        <options>
          <normal/>
        </options>
      </control>
      <!--_0x4e_1-->
      <control>
        <midino>0x4e</midino>
        <status>0x91</status>
        <description/>
        <group>[Channel2]</group>
        <key>hotcue_4_clear</key>
        <options>
          <normal/>
        </options>
      </control>
      <!--_0x09_0-->
      <control>
        <midino>0x09</midino>
        <status>0x90</status>
        <description/>
        <group>[Channel1]</group>
        <key>beatsync_tempo</key>
        <options>
          <normal/>
        </options>
      </control>
      <!--_0x09_1-->
      <control>
        <midino>0x09</midino>
        <status>0x91</status>
        <description/>
        <group>[Channel2]</group>
        <key>beatsync_tempo</key>
        <options>
          <normal/>
        </options>
      </control>
      <!--_0x04_0-->
      <control>
        <midino>0x04</midino>
        <status>0x90</status>
        <description/>
        <group>[Channel1]</group>
        <key>loop_halve</key>
        <options>
          <normal/>
        </options>
      </control>
      <!--_0x04_1-->
      <control>
        <midino>0x04</midino>
        <status>0x91</status>
        <description/>
        <group>[Channel2]</group>
        <key>loop_halve</key>
        <options>
          <normal/>
        </options>
      </control>
      <!--_0x28_0-->
      <control>
        <midino>0x28</midino>
        <status>0x90</status>
        <description/>
        <group>[Channel1]</group>
        <key>loop_double</key>
        <options>
          <normal/>
        </options>
      </control>
      <!--_0x28_1-->
      <control>
        <midino>0x28</midino>
        <status>0x91</status>
        <description/>
        <group>[Channel2]</group>
        <key>loop_double</key>
        <options>
          <normal/>
        </options>
      </control>
      <!--_0x43_0-->
      <control>
        <midino>0x43</midino>
        <status>0x90</status>
        <description/>
        <group>[Channel1]</group>
        <key>c.loopDoubleInverse</key>
        <options>
          <script-binding/>
        </options>
      </control>
      <!--_0x43_1-->
      <control>
        <midino>0x43</midino>
        <status>0x91</status>
        <description/>
        <group>[Channel2]</group>
        <key>c.loopDoubleInverse</key>
        <options>
          <script-binding/>
        </options>
      </control>
      <!--_0x67_0-->
      <control>
        <midino>0x67</midino>
        <status>0x90</status>
        <description/>
        <group>[Channel1]</group>
        <key>c.loopHalveInverse</key>
        <options>
          <script-binding/>
        </options>
      </control>
      <!--_0x67_1-->
      <control>
        <midino>0x67</midino>
        <status>0x91</status>
        <description/>
        <group>[Channel2]</group>
        <key>c.loopHalveInverse</key>
        <options>
          <script-binding/>
        </options>
      </control>
      <!--_0x08_0-->
      <control>
        <midino>0x08</midino>
        <status>0x90</status>
        <description/>
        <group>[Channel1]</group>
        <key>rate_temp_down_small</key>
        <options>
          <normal/>
        </options>
      </control>
      <!--_0x08_1-->
      <control>
        <midino>0x08</midino>
        <status>0x91</status>
        <description/>
        <group>[Channel2]</group>
        <key>rate_temp_down_small</key>
        <options>
          <normal/>
        </options>
      </control>
      <!--_0x02_0-->
      <control>
        <midino>0x02</midino>
        <status>0x90</status>
        <description/>
        <group>[Channel1]</group>
        <key>rate_temp_up_small</key>
        <options>
          <normal/>
        </options>
      </control>
      <!--_0x02_1-->
      <control>
        <midino>0x02</midino>
        <status>0x91</status>
        <description/>
        <group>[Channel2]</group>
        <key>rate_temp_up_small</key>
        <options>
          <normal/>
        </options>
      </control>
      <!--_0x2b_0-->
      <control>
        <midino>0x2b</midino>
        <status>0x90</status>
        <description/>
        <group>[Channel1]</group>
        <key>c.LoadSelectedTrack</key>
        <options>
          <script-binding/>
        </options>
      </control>
      <!--_0x2b_1-->
      <control>
        <midino>0x2b</midino>
        <status>0x91</status>
        <description/>
        <group>[Channel2]</group>
        <key>c.LoadSelectedTrack</key>
        <options>
          <script-binding/>
        </options>
      </control>
      <!--_0x20_0-->
      <control>
        <midino>0x20</midino>
        <status>0x90</status>
        <description/>
        <group>[Channel1]</group>
        <key>c.JogWheel_Hold</key>
        <options>
          <script-binding/>
        </options>
      </control>
      <!--_0x20_1-->
      <control>
        <midino>0x20</midino>
        <status>0x91</status>
        <description/>
        <group>[Channel2]</group>
        <key>c.JogWheel_Hold</key>
        <options>
          <script-binding/>
        </options>
      </control>
      <!--_0x2f_0-->
      <control>
        <midino>0x2f</midino>
        <status>0x90</status>
        <description/>
        <group>[Channel1]</group>
        <key>c.Scratch</key>
        <options>
          <script-binding/>
        </options>
      </control>
      <!--_0x2f_1-->
      <control>
        <midino>0x2f</midino>
        <status>0x91</status>
        <description/>
        <group>[Channel2]</group>
        <key>c.Scratch</key>
        <options>
          <script-binding/>
        </options>
      </control>
      <!--_0x13_0-->
      <control>
        <midino>0x13</midino>
        <status>0x90</status>
        <description/>
        <group>[Channel1]</group>
        <key>c.nudgeLoopStart</key>
        <options>
          <script-binding/>
        </options>
      </control>
      <!--_0x13_1-->
      <control>
        <midino>0x13</midino>
        <status>0x91</status>
        <description/>
        <group>[Channel2]</group>
        <key>c.nudgeLoopStart</key>
        <options>
          <script-binding/>
        </options>
      </control>
      <!--_0x0d_0-->
      <control>
        <midino>0x0d</midino>
        <status>0x90</status>
        <description/>
        <group>[Channel1]</group>
        <key>c.nudgeLoopEnd</key>
        <options>
          <script-binding/>
        </options>
      </control>
      <!--_0x0d_1-->
      <control>
        <midino>0x0d</midino>
        <status>0x91</status>
        <description/>
        <group>[Channel2]</group>
        <key>c.nudgeLoopEnd</key>
        <options>
          <script-binding/>
        </options>
      </control>
      <!--_0x52_0-->
      <control>
        <midino>0x52</midino>
        <status>0x90</status>
        <description/>
        <group>[Channel1]</group>
        <key>c.stepLoopBack</key>
        <options>
          <script-binding/>
        </options>
      </control>
      <!--_0x52_1-->
      <control>
        <midino>0x52</midino>
        <status>0x91</status>
        <description/>
        <group>[Channel2]</group>
        <key>c.stepLoopBack</key>
        <options>
          <script-binding/>
        </options>
      </control>
      <!--_0x4c_0-->
      <control>
        <midino>0x4c</midino>
        <status>0x90</status>
        <description/>
        <group>[Channel1]</group>
        <key>c.stepLoopForward</key>
        <options>
          <script-binding/>
        </options>
      </control>
      <!--_0x4c_1-->
      <control>
        <midino>0x4c</midino>
        <status>0x91</status>
        <description/>
        <group>[Channel2]</group>
        <key>c.stepLoopForward</key>
        <options>
          <script-binding/>
        </options>
      </control>
      <!--_0x16_0-->
      <control>
        <midino>0x16</midino>
        <status>0x90</status>
        <description/>
        <group>[Channel1]</group>
        <key>c.LoopIn</key>
        <options>
          <script-binding/>
        </options>
      </control>
      <!--_0x16_1-->
      <control>
        <midino>0x16</midino>
        <status>0x91</status>
        <description/>
        <group>[Channel2]</group>
        <key>c.LoopIn</key>
        <options>
          <script-binding/>
        </options>
      </control>
      <!--_0x2e_0-->
      <control>
        <midino>0x2e</midino>
        <status>0x90</status>
        <description/>
        <group>[Channel1]</group>
        <key>c.LoopOut</key>
        <options>
          <script-binding/>
        </options>
      </control>
      <!--_0x2e_1-->
      <control>
        <midino>0x2e</midino>
        <status>0x91</status>
        <description/>
        <group>[Channel2]</group>
        <key>c.LoopOut</key>
        <options>
          <script-binding/>
        </options>
      </control>
      <!--_0x22_0-->
      <control>
        <midino>0x22</midino>
        <status>0x90</status>
        <description/>
        <group>[Channel1]</group>
        <key>c.ReloopExit</key>
        <options>
          <script-binding/>
        </options>
      </control>
      <!--_0x22_1-->
      <control>
        <midino>0x22</midino>
        <status>0x91</status>
        <description/>
        <group>[Channel2]</group>
        <key>c.ReloopExit</key>
        <options>
          <script-binding/>
        </options>
      </control>
      <!--_0x1a_0-->
      <control>
        <midino>0x1a</midino>
        <status>0x90</status>
        <description/>
        <group>[Channel1]</group>
        <key>c.changeRateRange</key>
        <options>
          <script-binding/>
        </options>
      </control>
      <!--_0x1a_1-->
      <control>
        <midino>0x1a</midino>
        <status>0x91</status>
        <description/>
        <group>[Channel2]</group>
        <key>c.changeRateRange</key>
        <options>
          <script-binding/>
        </options>
      </control>
      <!--_0x26_0-->
      <control>
        <midino>0x26</midino>
        <status>0x90</status>
        <description/>
        <group>[Channel1]</group>
        <key>c.pitchZero</key>
        <options>
          <script-binding/>
        </options>
      </control>
      <!--_0x26_1-->
      <control>
        <midino>0x26</midino>
        <status>0x91</status>
        <description/>
        <group>[Channel2]</group>
        <key>c.pitchZero</key>
        <options>
          <script-binding/>
        </options>
      </control>
      <!--_0x03_0-->
      <control>
        <midino>0x03</midino>
        <status>0x90</status>
        <description/>
        <group>[Channel1]</group>
        <key>c.beat_tap</key>
        <options>
          <script-binding/>
        </options>
      </control>
      <!--_0x03_1-->
      <control>
        <midino>0x03</midino>
        <status>0x91</status>
        <description/>
        <group>[Channel2]</group>
        <key>c.beat_tap</key>
        <options>
          <script-binding/>
        </options>
      </control>
      <!--_0x21_0-->
      <control>
        <midino>0x21</midino>
        <status>0x90</status>
        <description/>
        <group>[Channel1]</group>
        <key>c.sensitivity1</key>
        <options>
          <script-binding/>
        </options>
      </control>
      <!--_0x21_1-->
      <control>
        <midino>0x21</midino>
        <status>0x91</status>
        <description/>
        <group>[Channel2]</group>
        <key>c.sensitivity1</key>
        <options>
          <script-binding/>
        </options>
      </control>
      <!--_0x27_0-->
      <control>
        <midino>0x27</midino>
        <status>0x90</status>
        <description/>
        <group>[Channel1]</group>
        <key>c.sensitivity2</key>
        <options>
          <script-binding/>
        </options>
      </control>
      <!--_0x27_1-->
      <control>
        <midino>0x27</midino>
        <status>0x91</status>
        <description/>
        <group>[Channel2]</group>
        <key>c.sensitivity2</key>
        <options>
          <script-binding/>
        </options>
      </control>
      <!--_0x2d_0-->
      <control>
        <midino>0x2d</midino>
        <status>0x90</status>
        <description/>
        <group>[Channel1]</group>
        <key>c.sensitivity3</key>
        <options>
          <script-binding/>
        </options>
      </control>
      <!--_0x2d_1-->
      <control>
        <midino>0x2d</midino>
        <status>0x91</status>
        <description/>
        <group>[Channel2]</group>
        <key>c.sensitivity3</key>
        <options>
          <script-binding/>
        </options>
      </control>
      <!--_0x71_0-->
      <control>
        <midino>0x71</midino>
        <status>0xb0</status>
        <description/>
        <group>[Playlist]</group>
        <key>c.PrevNextWheelShift</key>
        <options>
          <script-binding/>
        </options>
      </control>
      <!--_0x71_1-->
      <control>
        <midino>0x71</midino>
        <status>0xb1</status>
        <description/>
        <group>[Playlist]</group>
        <key>c.PrevNextWheelShift</key>
        <options>
          <script-binding/>
        </options>
      </control>
      <!--_0x32_0-->
      <control>
        <midino>0x32</midino>
        <status>0xb0</status>
        <description/>
        <group>[Channel1]</group>
        <key>c.PrevNextWheel</key>
        <options>
          <script-binding/>
        </options>
      </control>
      <!--_0x32_1-->
      <control>
        <midino>0x32</midino>
        <status>0xb1</status>
        <description/>
        <group>[Channel2]</group>
        <key>c.PrevNextWheel</key>
        <options>
          <script-binding/>
        </options>
      </control>
      <!--_0x74_0-->
      <control>
        <midino>0x74</midino>
        <status>0xb0</status>
        <description/>
        <group>[Channel1]</group>
        <key>c.JogZoom</key>
        <options>
          <script-binding/>
        </options>
      </control>
      <!--_0x74_1-->
      <control>
        <midino>0x74</midino>
        <status>0xb1</status>
        <description/>
        <group>[Channel2]</group>
        <key>c.JogZoom</key>
        <options>
          <script-binding/>
        </options>
      </control>
      <!--_0x35_0-->
      <control>
        <midino>0x35</midino>
        <status>0xb0</status>
        <description/>
        <group>[Channel1]</group>
        <key>c.JogWheel</key>
        <options>
          <script-binding/>
        </options>
      </control>
      <!--_0x35_1-->
      <control>
        <midino>0x35</midino>
        <status>0xb1</status>
        <description/>
        <group>[Channel2]</group>
        <key>c.JogWheel</key>
        <options>
          <script-binding/>
        </options>
      </control>
      <!--_0x15_0-->
      <control>
        <midino>0x15</midino>
        <status>0xb0</status>
        <description/>
        <group>[Channel1]</group>
        <key>c.back_fwd</key>
        <options>
          <script-binding/>
        </options>
      </control>
      <!--_0x15_1-->
      <control>
        <midino>0x15</midino>
        <status>0xb1</status>
        <description/>
        <group>[Channel2]</group>
        <key>c.back_fwd</key>
        <options>
          <script-binding/>
        </options>
      </control>
      <!--_0x5e_0-->
      <control>
        <midino>0x5e</midino>
        <status>0xe0</status>
        <description/>
        <group>[Channel1]</group>
        <key>rate</key>
        <options>
          <normal/>
        </options>
      </control>
      <!--_0x5e_1-->
      <control>
        <midino>0x5e</midino>
        <status>0xe1</status>
        <description/>
        <group>[Channel2]</group>
        <key>rate</key>
        <options>
          <normal/>
        </options>
      </control>
    </controls>
  </controller>
</MixxxMIDIPreset>
